{"HorizonLayout":[{"key":"VQFhZsYBvG","layout":"logo","menuIcon":{"name":"equal","fontFamily":"CupertinoIcons"},"showCart":true,"showLogo":false,"showMenu":true,"showSearch":true,"showNotification":false},{"fit":"fill","key":"IzyEYbuhsAz","items":[{"type":"image","image":"https://ik.imagekit.io/appbuilder/fluxbuilder/1755581377309_LYYV3lDuz.png","video":"","category":"22","products":[],"productLength":3,"showSubcategory":false,"bannerWithProduct":false,"defaultShowProduct":false},{"key":"QdvIOYEhXi","name":"","type":"image","image":"https://ik.imagekit.io/appbuilder/fluxbuilder/1755581402029_IaAupPYAOs.png","video":"","products":[],"productLength":3,"showSubcategory":false,"bannerWithProduct":false,"defaultShowProduct":false},{"type":"image","image":"https://ik.imagekit.io/appbuilder/fluxbuilder/1755581419450_o52s_3GQ1A.png","video":"","products":[],"productLength":3,"showSubcategory":false,"bannerWithProduct":false,"defaultShowProduct":false}],"design":"default","height":0.3,"isBlur":false,"isBulk":null,"layout":"bannerImage","radius":0,"padding":0,"autoPlay":true,"isSlider":true,"parallax":false,"upHeight":0,"isSoundOn":false,"marginTop":0,"marginLeft":0,"showNumber":false,"marginRight":0,"intervalTime":10,"isHorizontal":false,"isPreviewing":null,"marginBottom":0,"autoPlayVideo":false,"numberPadding":{"end":0,"top":15,"start":0,"bottom":0},"showIndicator":true,"showBackground":false,"numberAlignment":{"value":"topEnd"},"enableBackground":false,"indicatorPadding":{"end":0,"top":0,"start":0,"bottom":12},"pageIndicatorType":"line","indicatorAlignment":{"value":"bottomCenter"},"parallaxImageRatio":1.2,"enableTimeIndicator":true,"doubleTapToFullScreen":false},{"key":"hoFaXHriuiEr","size":1,"type":"image","wrap":false,"items":[{"tag":null,"name":null,"image":"https://ik.imagekit.io/appbuilder/fluxbuilder/1755581708934_ZZPPbK00C.avif","order":null,"title":"Tradition","colors":null,"onSale":false,"orderby":null,"category":"","featured":false,"showText":true,"description":null,"productType":false,"originalColor":true,"backgroundColor":null,"showDescription":false,"keepDefaultTitle":false,"productListAnimationConfig":null},{"tag":null,"name":null,"image":"https://trello.com/1/cards/68a22774237780236e051bd7/attachments/68a40d5369c2c6cab9edbe37/download/image_8.png","order":null,"title":"Featured Kurta","colors":null,"onSale":false,"orderby":null,"category":"","featured":false,"showText":true,"description":null,"productType":false,"originalColor":true,"backgroundColor":null,"showDescription":false,"keepDefaultTitle":false,"productListAnimationConfig":null},{"tag":null,"name":null,"image":"https://trello.com/1/cards/68a22774237780236e051bd7/attachments/68a40d9d28b30433062b7810/download/image_12.png","order":null,"title":"Elegant Dark","colors":null,"onSale":false,"orderby":null,"category":"","featured":false,"showText":true,"description":null,"productType":false,"originalColor":true,"backgroundColor":null,"showDescription":false,"keepDefaultTitle":false,"productListAnimationConfig":null},{"tag":null,"name":null,"image":"https://trello.com/1/cards/68a22774237780236e051bd7/attachments/68a40df75a257ae5ee359b15/download/image_11.png","order":null,"title":"Pista Green","colors":null,"onSale":false,"orderby":null,"category":"","featured":false,"showText":true,"description":null,"productType":false,"originalColor":true,"backgroundColor":null,"showDescription":false,"keepDefaultTitle":false,"productListAnimationConfig":null},{"tag":null,"name":null,"image":"https://trello.com/1/cards/68a22774237780236e051bd7/attachments/68a40e2b1bd4f79c96519814/download/image_13.png","order":null,"title":"Soft Green","colors":null,"onSale":false,"orderby":null,"category":"","featured":false,"showText":true,"description":null,"productType":false,"originalColor":true,"backgroundColor":null,"showDescription":false,"keepDefaultTitle":false,"productListAnimationConfig":null},{"tag":null,"name":null,"image":"https://trello.com/1/cards/68a22774237780236e051bd7/attachments/68a40f5dec1955f264b34c43/download/Rectangle_22.png","order":null,"title":"Favorite","colors":null,"onSale":false,"orderby":null,"category":"","featured":false,"showText":true,"description":null,"productType":false,"originalColor":true,"backgroundColor":null,"showDescription":false,"keepDefaultTitle":false,"productListAnimationConfig":null}],"border":0.6,"isBulk":false,"layout":"category","radius":80,"shadow":null,"columns":null,"marginX":0,"marginY":0,"spacing":12,"itemSize":{"width":126,"height":160},"paddingX":10,"paddingY":10,"hideTitle":false,"marginTop":22,"marginLeft":0,"imageBoxFit":"fitWidth","marginRight":0,"enableBorder":false,"imageSpacing":10,"isPreviewing":null,"marginBottom":22,"noBackground":false,"gradientStyle":false,"labelFontSize":14,"originalColor":false,"separateWidth":24,"textAlignment":"topCenter","horizontalItem":false,"animationConfig":null,"enableBackground":null,"imageBorderColor":"FF041239","imageBorderStyle":"dot","imageBorderWidth":1.5,"productCategoryMenuStyle":"menu","allowFilterMultipleCategory":false},{"key":"RvkmEWcMYPhkyX","name":"Our Collections","rows":2,"isBulk":null,"layout":"threeColumn","onSale":false,"columns":0,"hMargin":6,"useSort":false,"vMargin":0,"featured":false,"hPadding":8,"parallax":false,"vPadding":0,"hidePrice":false,"hideStore":false,"hideTitle":false,"showHeart":false,"cardDesign":"simpleForWeb","imageRatio":1.032813970726657,"isSnapping":false,"imageBoxfit":"cover","borderRadius":15,"enableRating":true,"isPreviewing":null,"showCartIcon":false,"showCategory":false,"showQuantity":false,"openInWebview":false,"showCountDown":false,"showOnlyImage":false,"advancedParams":{},"cartIconRadius":20,"showCartButton":false,"showStockStatus":true,"backgroundRadius":10,"enableAutoSliding":false,"showCartIconColor":true,"useCircularRadius":true,"parallaxImageRatio":1.2,"enableBottomAddToCart":false,"productListItemHeight":125,"cartButtonQuantitySize":40,"hideEmptyProductLayout":false,"hideEmptyProductListRating":false,"showCartButtonWithQuantity":false},{"key":"VJrUSgsVuRiwwuq","name":"Latest News And Blog","isBulk":null,"layout":"blog","radius":9,"hMargin":6,"include":[],"padding":12,"vMargin":0,"hideDate":false,"hideTitle":false,"cardDesign":"simple","hideAuthor":false,"isSnapping":false,"hideComment":true,"imageBorder":3,"innerPadding":4,"isPreviewing":null,"showOnlyImage":false,"enableBackground":false,"enableAutoSliding":true,"durationAutoSliding":1},{"key":"mdHHQjpfQN","name":"Our Customer's Favorite ⭐️","rows":1,"isBulk":null,"layout":"threeColumn","onSale":false,"columns":0,"hMargin":9,"useSort":false,"vMargin":18,"category":"gid://shopify/Collection/526353301805","featured":false,"hPadding":8,"parallax":false,"vPadding":0,"boxShadow":{"x":7,"y":9,"blurRadius":10,"colorOpacity":0.1,"spreadRadius":10},"hidePrice":false,"hideStore":false,"hideTitle":false,"marginBGP":{"top":0,"left":0,"right":0,"bottom":1.9},"showHeart":false,"cardDesign":"simpleForWeb","imageRatio":1.2,"isSnapping":true,"spaceWidth":2,"imageBoxfit":"cover","borderRadius":12,"enableRating":false,"isPreviewing":null,"showCartIcon":true,"showCategory":false,"showQuantity":false,"openInWebview":false,"showCountDown":false,"showOnlyImage":false,"advancedParams":{},"cartIconRadius":9,"showCartButton":false,"backgroundColor":"ff041239","showStockStatus":false,"backgroundHeight":183,"backgroundRadius":0,"enableAutoSliding":false,"showCartIconColor":false,"useCircularRadius":true,"parallaxImageRatio":1.2,"enableBottomAddToCart":false,"productListItemHeight":150,"cartButtonQuantitySize":40,"hideEmptyProductLayout":false,"hideEmptyProductListRating":false,"showCartButtonWithQuantity":false},{"key":"kyeDgAqlnF","size":1,"type":"image","wrap":false,"items":[{"tag":null,"name":null,"image":"https://trello.com/1/cards/68a22774237780236e051bd7/attachments/68a4266d42a2efa32b8e98c0/download/image_13.png","order":null,"title":"Soft Green Kurta","colors":null,"onSale":false,"orderby":null,"category":"gid://shopify/Collection/526654636333","featured":false,"showText":true,"description":"","productType":false,"originalColor":false,"backgroundColor":null,"showDescription":false,"keepDefaultTitle":false,"productListAnimationConfig":null},{"tag":null,"name":null,"image":"https://trello.com/1/cards/68a22774237780236e051bd7/attachments/68a42657e7a1bc1284996a2c/download/image_11.png","order":null,"title":"Pista Green Kurta","colors":null,"onSale":false,"orderby":null,"category":"gid://shopify/Collection/526654800173","featured":false,"showText":true,"description":"","productType":false,"originalColor":false,"backgroundColor":null,"showDescription":false,"keepDefaultTitle":false,"productListAnimationConfig":null},{"tag":null,"name":null,"image":"https://trello.com/1/cards/68a22774237780236e051bd7/attachments/68a425293917d85b92abcb47/download/image_12.png","order":null,"title":"Elegant Dark Kurta","colors":null,"onSale":false,"orderby":null,"category":"gid://shopify/Collection/526654865709","featured":false,"showText":true,"description":"","productType":false,"originalColor":false,"backgroundColor":null,"showDescription":false,"keepDefaultTitle":false,"productListAnimationConfig":null}],"isBulk":null,"layout":"category","radius":4,"shadow":null,"columns":null,"marginX":0,"marginY":0,"spacing":12,"itemSize":{"width":115,"height":214},"paddingX":0,"paddingY":0,"hideTitle":false,"marginTop":24,"marginLeft":9,"imageBoxFit":"cover","marginRight":9,"enableBorder":true,"imageSpacing":0,"isPreviewing":null,"marginBottom":25,"noBackground":false,"gradientStyle":false,"labelFontSize":14,"originalColor":false,"separateWidth":24,"textAlignment":"topLeft","horizontalItem":false,"animationConfig":null,"enableBackground":null,"imageBorderStyle":"solid","imageBorderWidth":0,"productCategoryMenuStyle":"menu","allowFilterMultipleCategory":false},{"key":"HGpxBXLaBL","type":"custom","items":[{"name":"John Alethea","type":"card","major":"Customer","avatar":"https://trello.com/1/cards/60efb9b97be65b6792f8f836/attachments/61a9ba3e97f20d84a0ef074d/previews/61a9ba4097f20d84a0ef07ba/download/1178_U1RVRElPIEtBVCAxNDEtNDQ.jpg","isLeft":true,"boxShadow":{"x":4,"y":2,"blurRadius":2.0202020202020203,"colorOpacity":0.1,"spreadRadius":0},"marginTop":0,"marginLeft":10,"authorInTop":false,"borderWidth":0.2,"marginRight":10,"testimonial":"I recently purchased a kurta from this brand and honestly, I’m beyond impressed. The fabric feels so luxurious, and the fit was like it was custom-made for me. I wore it to a wedding and got so many compliments- it made me feel confident and stylish.","borderRadius":5,"marginBottom":0,"backgroundColor":"FF041239"},{"name":"John Blethea","type":"card","major":"Shipper","avatar":"https://trello.com/1/cards/60efb9b97be65b6792f8f836/attachments/61b1c4d17c691a149e4fd8ea/previews/61b1c4d27c691a149e4fd9d2/download/beard.png","isLeft":true,"boxShadow":{"x":4,"y":2,"blurRadius":2.0202020202020203,"colorOpacity":0.1,"spreadRadius":0},"marginTop":0,"marginLeft":10,"authorInTop":false,"borderWidth":0.2,"marginRight":10,"testimonial":"Lurnrm dignissim tincidunt mauris, eu egestas lorem pretium et. Integer blandit tortor non. Etiam sollicitudin sollicitudin nisl ac ultrices. Phasellus nec volutpat velit. Nulla facilisi. Aenean eu ex nisl. Aenean efficitur in nisi ac vulputate. Donec quis varius lacus. Donec in malesuada ligula. In fermentum erat ut nunc lobortis, ut posuere magna luctus. In sodales eleifend interdum. Vivamus fringilla quam sed erat blandit venenatis. ","borderRadius":5,"marginBottom":0,"backgroundColor":"FF041239"},{"name":"Adam Ave","type":"card","major":"Customer","avatar":"https://trello.com/1/cards/60efb9b97be65b6792f8f836/attachments/61b1c4d17c691a149e4fd8ea/previews/61b1c4d27c691a149e4fd9d2/download/beard.png","isLeft":true,"marginTop":0,"marginLeft":0,"authorInTop":false,"borderWidth":0,"marginRight":0,"testimonial":"Donec quis varius lacus. Etiam sollicitudin sollicitudin nisl ac ultrices. Phasellus nec volutpat velit. Nulla facilisi. Aenean eu ex nisl. Aenean efficitur in nisi ac vulputate. Donec in malesuada ligula. In fermentum erat ut nunc lobortis, ut posuere magna luctus. In sodales eleifend interdum. Vivamus fringilla quam sed erat blandit venenatis. Praesent dignissim tincidunt mauris, eu egestas lorem pretium et. Integer blandit tortor non.","borderRadius":5,"marginBottom":0,"backgroundColor":"FF041239"}],"height":250,"isBulk":null,"layout":"sliderTestimonial","autoPlay":true,"marginTop":20,"marginLeft":5,"marginRight":5,"intervalTime":3,"isPreviewing":null,"marginBottom":14,"enableBackground":false},{"key":"HDYbtSiLCh","name":"Trending Collections","rows":1,"isBulk":null,"layout":"threeColumn","onSale":false,"columns":0,"hMargin":6,"useSort":false,"vMargin":0,"category":"gid://shopify/Collection/526354514221","featured":false,"hPadding":9,"parallax":false,"vPadding":2,"hidePrice":false,"hideStore":false,"hideTitle":false,"showHeart":false,"cardDesign":"simpleForWeb","imageRatio":1.2,"isSnapping":false,"paddingBGP":{"top":36.58208631931391,"left":0,"right":0,"bottom":0},"spaceWidth":145,"imageBoxfit":"cover","borderRadius":21,"enableRating":true,"isPreviewing":null,"showCartIcon":true,"showCategory":false,"showQuantity":false,"openInWebview":false,"showCountDown":false,"showOnlyImage":false,"advancedParams":{},"cartIconRadius":9,"showCartButton":false,"backgroundColor":"ff041239","backgroundImage":"https://ik.imagekit.io/appbuilder/fluxbuilder/1755667646773_tEq6Wkp51u.png","showStockStatus":true,"backgroundBoxFit":"cover","backgroundHeight":325,"backgroundRadius":0,"enableAutoSliding":false,"showCartIconColor":false,"useCircularRadius":true,"parallaxImageRatio":1.2,"enableBottomAddToCart":false,"productListItemHeight":125,"cartButtonQuantitySize":40,"hideEmptyProductLayout":false,"hideEmptyProductListRating":false,"showCartButtonWithQuantity":false}],"Setting":{"ShowChat":true,"MainColor":null,"FontFamily":"Roboto","FontHeader":"ABeeZee","StickyHeader":true,"TabBarConfig":{"color":"ff626367","enable":true,"iconSize":22.955647901669458,"colorCart":"fffe2060","colorIcon":"ffffffff","marginTop":0,"isSafeArea":false,"marginLeft":14.976930273759336,"paddingTop":9.960136747221199,"enableOnTop":false,"marginRight":15.012519286150008,"paddingLeft":0,"marginBottom":14.973564791065872,"paddingRight":0,"showFloating":false,"showMinimize":false,"enableDivider":false,"paddingBottom":10.006131677365229,"radiusTopLeft":15.079123349164956,"TabBarFloating":{"color":null,"width":50,"height":50,"radius":50,"location":null,"position":0,"elevation":2,"isCoverMode":false,"notchMargin":4,"floatingType":"rectangle"},"indicatorStyle":"rectangular","radiusTopRight":15.047170605431592,"TabBarIndicator":{"color":"ff878f8f","height":0,"radius":0,"strokeWidth":0,"tabPosition":"bottom","paintingStyle":"fill","topLeftRadius":9.266948361796246,"topRightRadius":9.138236789907289,"verticalPadding":0,"bottomLeftRadius":9.173194264700902,"bottomRightRadius":8.866903346613203,"horizontalPadding":10.01247069941136,"distanceFromCenter":0},"colorActiveIcon":"ffffffff","alwaysShowTabBar":false,"radiusBottomLeft":15.03100081501931,"showFloatingClip":true,"radiusBottomRight":15.034404981421897},"ProductDetail":"simpleType","AgeRestriction":{"title":"Welcome to our shop\nYou must be 21 or older to enter","enable":false,"useLogo":true,"imageUrl":"","minimumAge":21,"hintMessage":"What is your year of birth?","deniedMessage":"You are not of legal age to use this application","alwaysShowUponOpen":true,"backgroundImageUrl":""},"ProductListLayout":"list","SmartEngagementBanner":{"popup":{"data":{"fit":"fitHeight","key":"p2oq4zc4hg","items":[{"image":"https://i.imgur.com/ZL1LO75.png","padding":0,"category":"22","products":[],"showSubcategory":false,"bannerWithProduct":false,"defaultShowProduct":false}],"design":"static","height":0.45,"layout":"bannerImage","parallax":false,"marginTop":10,"marginLeft":null,"marginRight":null,"isHorizontal":false,"marginBottom":10,"enableParallax":false,"parallaxImageRatio":1.2},"enable":false,"updatedTime":1661314494281,"closePosition":"topRight","alwaysShowUponOpen":true},"sticky":{"data":{"fit":"fitWidth","key":"ga8oe39k5t","items":[{"image":"https://i.imgur.com/LUaEM3v.jpeg","coupon":"halfprice","radius":9,"padding":0,"products":[],"showSubcategory":false,"bannerWithProduct":false,"defaultShowProduct":false}],"design":"static","height":0.2,"layout":"bannerImage","parallax":false,"marginTop":10,"marginLeft":10,"marginRight":10,"isHorizontal":false,"marginBottom":10,"enableParallax":false,"parallaxImageRatio":1.2},"enable":false},"flexible":{"data":{"items":[{"image":"https://assets9.lottiefiles.com/private_files/lf30_a4mKwA.json","width":100,"height":80,"navigator":{"coupon":"blackf","showSubcategory":false},"marginLeft":0,"marginRight":0,"useMaxWidth":true,"borderRadius":2,"textFontSize":14}],"layout":"button","alignment":"topCenter","marginTop":0,"marginBottom":0},"width":100,"enable":false,"height":100,"canDrag":true,"canClose":true}}},"TabBar":[{"key":"RMCJenqhPb","pos":100,"icon":"home","layout":"home","visible":true,"fontFamily":"CupertinoIcons","fullscreen":false,"showOriginalColor":false},{"key":"UpJErWLiuR","pos":200,"icon":"rectangle_grid_1x2","layout":"category","visible":true,"parallax":false,"defaultTab":false,"fontFamily":"CupertinoIcons","fullscreen":false,"showQRCode":true,"showSearch":true,"categoryLayout":"fancy-scroll","showOriginalColor":false,"parallaxImageRatio":1.2},{"key":"vXWRVkjLWB","pos":300,"icon":"gear_big","layout":"profile","settings":["biometrics","wishlist","notifications","language","currencies","darkTheme","order","rating","privacy"],"styleItem":"listTile","background":"https://trello.com/1/cards/68a22774237780236e051bd7/attachments/68a567c6d772114e1bc20538/download/gears-3d-modern-illustration-on-dark-blue-background-vector.jpg","drawerIcon":{"icon":"equal","fontFamily":"CupertinoIcons"},"fontFamily":"CupertinoIcons","fullscreen":false,"showBackground":true,"showOriginalColor":false,"subGeneralSetting":{"about":{},"privacy":{"webUrl":"https://vedkartstore.myshopify.com/pages/privacy-policy"}}},{"key":"NSLWSoohMh","pos":400,"icon":"bag","layout":"cart","fontFamily":"CupertinoIcons","categoryLayout":"cart"},{"key":"DzDiCvqksN","data":{"id":1,"container":{"image":{"url":"https://images.unsplash.com/photo-1584352587534-5763683125b5?ixlib=rb-1.2.1&ixid=eyJhcHBfaWQiOjEyMDd9&auto=format&fit=crop&w=2700&q=80","align":{"x":1,"y":1},"width":1,"height":0.5},"header":{"text":"About US","align":{"x":-1,"y":0.8},"color":"#FFFFFF","padding":{"vertical":10,"horizontal":20},"background":"#000000"},"height":0.5},"subHeader":"This is sub heading","description":"This is description"},"icon":"assets/icons/tabs/icon-heartthin.png","layout":"static","visible":false,"fullscreen":false,"showOriginalColor":false},{"key":"XAfssRzdmk","icon":"doc_text","layout":"list-blog","visible":true,"defaultTab":false,"fontFamily":"CupertinoIcons","fullscreen":false,"showOriginalColor":false}],"AppBar":{"snap":true,"items":[{"pos":100,"icon":"person","size":44,"type":"text","radius":0,"fontSize":16,"iconSize":24,"alignment":"center","marginTop":0,"fontFamily":"CupertinoIcons","fontWeight":"400","marginLeft":0,"paddingTop":0,"marginRight":0,"paddingLeft":0,"spacingText":3,"textOpacity":0.5,"avatarRadius":100,"marginBottom":0,"paddingRight":0,"paddingBottom":0,"headerFontSize":16,"headerFontWeight":"400","headerTextOpacity":0.5}],"enable":false,"pinned":true,"floating":true,"elevation":0,"showOnScreens":["home"],"alwaysShowAppBar":false},"Drawer":{"key":"CQFPsKjLhn","logo":null,"items":[{"show":true,"type":"login"},{"show":true,"type":"home"},{"show":true,"type":"categories"},{"show":true,"type":"blog"},{"show":true,"type":"cart"},{"show":true,"type":"profile"},{"show":false,"type":"category"},{"show":true,"type":"web-FSIrhgChbR"},{"type":"web-VSjIdbojnX","show":true},{"type":"web-liUJULnQkQ","show":true},{"type":"web-miWleWhtOI","show":true},{"type":"web-QvgpFVGBHS","show":true},{"type":"web-jDGAfaEobR","show":true},{"type":"web-FUIFfuqxCh","show":true},{"type":"web-HBNFbZlghC","show":true},{"show":false,"type":"screen-sRakYyEuVl"}],"enable":true,"filter":0,"logoDark":null,"safeArea":true,"iconColor":null,"textColor":null,"logoConfig":{"height":38,"marginLeft":0,"marginRight":0,"marginTop":60,"marginBottom":10,"boxFit":"cover"},"zoomConfig":null,"colorFilter":null,"subDrawerItem":{"web-FSIrhgChbR":{"id":"web-12","icon":"info","title":"Terms & Condition","webUrl":"https://vedkartstore.myshopify.com/pages/app-terms-condition","buttons":[],"enableClose":false,"webViewMode":true,"bannerHeight":15,"useTabScreen":false,"enableDivider":false,"enableForward":false,"requiredLogin":false,"enableBackward":false,"iconFontFamily":"CupertinoIcons","buttonAlignment":"centerLeft"},"screen-sRakYyEuVl":{"id":"web-12","icon":"news","title":"","screen":"home","buttons":[],"enableClose":false,"webViewMode":false,"bannerHeight":15,"useTabScreen":false,"enableDivider":false,"enableForward":false,"requiredLogin":false,"enableBackward":true,"iconFontFamily":"CupertinoIcons","buttonAlignment":"centerLeft"},"web-VSjIdbojnX":{"id":"web-12","title":"Privacy Policy","icon":"arrow_2_circlepath","iconFontFamily":"CupertinoIcons","webUrl":"https://vedkartstore.myshopify.com/pages/app-privacy-policy","enableDivider":false,"webViewMode":true,"requiredLogin":false,"enableForward":false,"enableBackward":true,"enableClose":false,"buttonAlignment":"centerLeft","buttons":[],"bannerHeight":15,"screen":"home","useTabScreen":false},"web-miWleWhtOI":{"id":"web-12","title":"Shipping Policy","icon":"checkmark_shield","iconFontFamily":"CupertinoIcons","webUrl":"https://vedkartstore.myshopify.com/pages/app-shipping-shop","enableDivider":false,"webViewMode":true,"requiredLogin":false,"enableForward":false,"enableBackward":true,"enableClose":false,"buttonAlignment":"centerLeft","buttons":[],"bannerHeight":15,"useTabScreen":false},"web-QvgpFVGBHS":{"id":"web-12","title":"FAQs","icon":"equal_square","iconFontFamily":"CupertinoIcons","webUrl":"https://vedkartstore.myshopify.com/pages/app-faq","enableDivider":false,"webViewMode":true,"requiredLogin":false,"enableForward":false,"enableBackward":true,"enableClose":false,"buttonAlignment":"centerLeft","buttons":[],"bannerHeight":15,"useTabScreen":false},"web-jDGAfaEobR":{"id":"web-12","title":"Size Guide","icon":"chart_bar_square","iconFontFamily":"CupertinoIcons","webUrl":"https://vedkartstore.myshopify.com/pages/app-size-guide","enableDivider":false,"webViewMode":true,"requiredLogin":false,"enableForward":false,"enableBackward":true,"enableClose":false,"buttonAlignment":"centerLeft","buttons":[],"bannerHeight":15,"useTabScreen":false},"web-FUIFfuqxCh":{"id":"web-12","title":"Contact Us","icon":"plus_circled","iconFontFamily":"CupertinoIcons","webUrl":"https://vedkartstore.myshopify.com/pages/app-contact-us","enableDivider":false,"webViewMode":true,"requiredLogin":false,"enableForward":false,"enableBackward":true,"enableClose":false,"buttonAlignment":"centerLeft","buttons":[],"bannerHeight":15,"useTabScreen":false},"web-HBNFbZlghC":{"id":"web-12","title":"About Us","icon":"checkmark_alt_circle_fill","iconFontFamily":"CupertinoIcons","webUrl":"https://vedkartstore.myshopify.com/pages/app-about-us","enableDivider":false,"webViewMode":true,"requiredLogin":false,"enableForward":false,"enableBackward":true,"enableClose":false,"buttonAlignment":"centerLeft","buttons":[],"bannerHeight":15,"screen":"profile","useTabScreen":false},"web-liUJULnQkQ":{"id":"web-12","title":"Return & Refund Policy","icon":"return_icon","iconFontFamily":"CupertinoIcons","webUrl":"https://vedkartstore.myshopify.com/pages/app-return-refund-policy","enableDivider":false,"webViewMode":true,"requiredLogin":false,"enableForward":false,"enableBackward":true,"enableClose":false,"buttonAlignment":"centerLeft","buttons":[],"bannerHeight":15,"useTabScreen":false}},"backgroundColor":null,"backgroundImage":null},"overrideTranslation":{"@@locale":"en","startShopping":"Shop now"},"Datetime":"16:31:20 - Sat 23 Aug"}